setup.cfg
setup.py
PyDEGIRO.egg-info/PKG-INFO
PyDEGIRO.egg-info/SOURCES.txt
PyDEGIRO.egg-info/dependency_links.txt
PyDEGIRO.egg-info/top_level.txt
PyDegiro/__init__.py
PyDegiro/consts.py
PyDegiro/main.py