Metadata-Version: 1.0
Name: PyDEGIRO
Version: 1.0.0
Summary: Unofficial python API of DEGIRO patform
Home-page: https://github.com/a-wakeel/PyDEGIRO
Author: awakeel
Author-email: awkhan978@gmail.com
License: GPL
Platform: UNKNOWN
